{
  "main": {
    "id": "92d44004e24a1523",
    "type": "split",
    "children": [
      {
        "id": "4f32e7ca575af399",
        "type": "tabs",
        "children": [
          {
            "id": "ecbc9632cb85bf35",
            "type": "leaf",
            "state": {
              "type": "markdown",
              "state": {
                "file": "_index.md",
                "mode": "source",
                "source": false
              }
            }
          }
        ]
      }
    ],
    "direction": "vertical"
  },
  "left": {
    "id": "10ea151f1eca1599",
    "type": "split",
    "children": [
      {
        "id": "8fafd9c853635fb8",
        "type": "tabs",
        "children": [
          {
            "id": "3fa6024f8bb26fb4",
            "type": "leaf",
            "state": {
              "type": "file-explorer",
              "state": {
                "sortOrder": "alphabetical"
              }
            }
          },
          {
            "id": "3529af5ff6976da8",
            "type": "leaf",
            "state": {
              "type": "search",
              "state": {
                "query": "",
                "matchingCase": false,
                "explainSearch": false,
                "collapseAll": false,
                "extraContext": false,
                "sortOrder": "alphabetical"
              }
            }
          },
          {
            "id": "d7c6168221e2340d",
            "type": "leaf",
            "state": {
              "type": "bookmarks",
              "state": {}
            }
          }
        ]
      }
    ],
    "direction": "horizontal",
    "width": 300
  },
  "right": {
    "id": "34fbf74ec12e421c",
    "type": "split",
    "children": [
      {
        "id": "ad29293b641caebc",
        "type": "tabs",
        "children": [
          {
            "id": "038f7d801eacd8e1",
            "type": "leaf",
            "state": {
              "type": "backlink",
              "state": {
                "file": "_index.md",
                "collapseAll": false,
                "extraContext": false,
                "sortOrder": "alphabetical",
                "showSearch": false,
                "searchQuery": "",
                "backlinkCollapsed": false,
                "unlinkedCollapsed": true
              }
            }
          },
          {
            "id": "813cf67805d45797",
            "type": "leaf",
            "state": {
              "type": "outgoing-link",
              "state": {
                "file": "_index.md",
                "linksCollapsed": false,
                "unlinkedCollapsed": true
              }
            }
          },
          {
            "id": "5364e04c91586780",
            "type": "leaf",
            "state": {
              "type": "tag",
              "state": {
                "sortOrder": "frequency",
                "useHierarchy": true
              }
            }
          },
          {
            "id": "759090ae8aee5b82",
            "type": "leaf",
            "state": {
              "type": "outline",
              "state": {
                "file": "_index.md"
              }
            }
          }
        ],
        "currentTab": 3
      }
    ],
    "direction": "horizontal",
    "width": 315.5
  },
  "left-ribbon": {
    "hiddenItems": {
      "switcher:打开快速切换": false,
      "canvas:新建白板": false,
      "daily-notes:打开/创建今天的日记": false,
      "templates:插入模板": false,
      "command-palette:打开命令面板": false
    }
  },
  "active": "ecbc9632cb85bf35",
  "lastOpenFiles": [
    "admin/_index.md",
    "环境配置/_index.md",
    "环境配置/python/使用Anaconda轻松管理python虚拟环境与安装第三方包.md",
    "环境配置/python/pip设置代理.md",
    "环境配置/python/pip换源.md",
    "admin",
    "_index.md",
    "简介/_index.md",
    "简介",
    "新建文件夹",
    "项目",
    "笔记专栏/算法笔记/_index.md",
    "笔记专栏/算法笔记",
    "笔记专栏/AI论文/_index.md",
    "笔记专栏/AI论文",
    "笔记专栏/hugo博客/_index.md",
    "笔记专栏/hugo博客",
    "笔记专栏/pytorch/_index.md",
    "笔记专栏/pytorch",
    "笔记专栏/深度学习/_index.md",
    "笔记专栏/深度学习",
    "笔记专栏/环境配置/玩机技巧/油猴脚本.md",
    "笔记专栏/环境配置/玩机技巧/_index.md",
    "笔记专栏/环境配置/python/使用Anaconda轻松管理python虚拟环境与安装第三方包.md",
    "笔记专栏/环境配置/python/_index.md",
    "笔记专栏/环境配置/python/pytorch安装教程.md",
    "笔记专栏/环境配置/python/pip设置代理.md",
    "笔记专栏/环境配置/python/pip换源.md",
    "笔记专栏/环境配置/玩机技巧",
    "笔记专栏/环境配置/_index.md",
    "pytorch/_index.md",
    "AI论文/_index.md",
    "算法笔记/_index.md",
    "深度学习/_index.md",
    "hugo博客/_index.md",
    "环境配置/玩机技巧/油猴脚本.md",
    "环境配置/玩机技巧/attachments/rjaoa.png",
    "环境配置/玩机技巧/attachments/rjaoa.webp",
    "环境配置/玩机技巧/attachments/t99uj.webp",
    "环境配置/玩机技巧/attachments/y2r37.webp",
    "环境配置/玩机技巧/attachments/a0gsz.webp",
    "环境配置/玩机技巧/attachments/90bgt.webp",
    "环境配置/玩机技巧/attachments/ucynr.webp",
    "环境配置/玩机技巧/attachments/qlkkn.webp",
    "环境配置/玩机技巧/attachments/g7mj3.webp",
    "环境配置/玩机技巧/attachments/gpb5k.webp"
  ]
}